[{"d":317069,"n":"الاثنين","s_d":32,"s_m":"فبراير","l_d":5.3899999999877934,"l_m":"صفر","year":869,"status":"كبس"},{"d":317070,"n":"الثلاثاء","s_d":33,"s_m":"فبراير","l_d":6.3899999999877934,"l_m":"ربيع الأول","year":869,"status":"كبس"},{"d":317071,"n":"الأربعاء","s_d":34,"s_m":"فبراير","l_d":7.3899999999877934,"l_m":"ربيع الأول","year":869,"status":"كبس"},{"d":317072,"n":"الخميس","s_d":35,"s_m":"فبراير","l_d":8.389999999987793,"l_m":"ربيع الثاني","year":869,"status":"كبس"},{"d":317073,"n":"الجمعة","s_d":36,"s_m":"فبراير","l_d":9.389999999987793,"l_m":"ربيع الثاني","year":869,"status":"كبس"},{"d":317074,"n":"السبت","s_d":37,"s_m":"فبراير","l_d":10.389999999987793,"l_m":"ربيع الثاني","year":869,"status":"كبس"},{"d":317075,"n":"الأحد","s_d":38,"s_m":"فبراير","l_d":11.389999999987793,"l_m":"جمادى الأول","year":869,"status":"كبس"},{"d":317076,"n":"الاثنين","s_d":39,"s_m":"فبراير","l_d":12.389999999987793,"l_m":"جمادى الأول","year":869,"status":"كبس"},{"d":317077,"n":"الثلاثاء","s_d":40,"s_m":"فبراير","l_d":13.389999999987793,"l_m":"جمادى الثاني","year":869,"status":"كبس"},{"d":317078,"n":"الأربعاء","s_d":41,"s_m":"فبراير","l_d":14.389999999987793,"l_m":"جمادى الثاني","year":869,"status":"كبس"},{"d":317079,"n":"الخميس","s_d":42,"s_m":"فبراير","l_d":15.389999999987793,"l_m":"جمادى الثاني","year":869,"status":"كبس"},{"d":317080,"n":"الجمعة","s_d":43,"s_m":"فبراير","l_d":16.389999999987793,"l_m":"رجب","year":869,"status":"كبس"},{"d":317081,"n":"السبت","s_d":44,"s_m":"فبراير","l_d":17.389999999987793,"l_m":"رجب","year":869,"status":"كبس"},{"d":317082,"n":"الأحد","s_d":45,"s_m":"فبراير","l_d":18.389999999987793,"l_m":"شعبان","year":869,"status":"كبس"},{"d":317083,"n":"الاثنين","s_d":46,"s_m":"فبراير","l_d":19.389999999987793,"l_m":"شعبان","year":869,"status":"كبس"},{"d":317084,"n":"الثلاثاء","s_d":47,"s_m":"فبراير","l_d":20.389999999987793,"l_m":"شعبان","year":869,"status":"كبس"},{"d":317085,"n":"الأربعاء","s_d":48,"s_m":"فبراير","l_d":21.389999999987793,"l_m":"رمضان","year":869,"status":"كبس"},{"d":317086,"n":"الخميس","s_d":49,"s_m":"فبراير","l_d":22.389999999987793,"l_m":"رمضان","year":869,"status":"كبس"},{"d":317087,"n":"الجمعة","s_d":50,"s_m":"فبراير","l_d":23.389999999987793,"l_m":"شوال","year":869,"status":"كبس"},{"d":317088,"n":"السبت","s_d":51,"s_m":"فبراير","l_d":24.389999999987793,"l_m":"شوال","year":869,"status":"كبس"},{"d":317089,"n":"الأحد","s_d":52,"s_m":"فبراير","l_d":25.389999999987793,"l_m":"شوال","year":869,"status":"كبس"},{"d":317090,"n":"الاثنين","s_d":53,"s_m":"فبراير","l_d":26.389999999987793,"l_m":"ذو القعدة","year":869,"status":"كبس"},{"d":317091,"n":"الثلاثاء","s_d":54,"s_m":"فبراير","l_d":27.389999999987793,"l_m":"ذو القعدة","year":869,"status":"كبس"},{"d":317092,"n":"الأربعاء","s_d":55,"s_m":"فبراير","l_d":28.389999999987793,"l_m":"ذو الحجة","year":869,"status":"كبس"},{"d":317093,"n":"الخميس","s_d":56,"s_m":"فبراير","l_d":29.389999999987793,"l_m":"ذو الحجة","year":869,"status":"كبس"},{"d":317094,"n":"الجمعة","s_d":57,"s_m":"فبراير","l_d":30.389999999987793,"l_m":"ذو الحجة","year":869,"status":"كبس"},{"d":317095,"n":"السبت","s_d":58,"s_m":"فبراير","l_d":1.8599999999877923,"l_m":"محرم","year":869,"status":"كبس"},{"d":317096,"n":"الأحد","s_d":59,"s_m":"فبراير","l_d":2.8599999999877923,"l_m":"محرم","year":869,"status":"كبس"},{"d":317097,"n":"الاثنين","s_d":60,"s_m":"فبراير","l_d":3.8599999999877923,"l_m":"صفر","year":869,"status":"كبس"},{"d":317098,"n":"الثلاثاء","s_d":61,"s_m":"مارس","l_d":4.859999999987792,"l_m":"صفر","year":869,"status":"كبس"},{"d":317099,"n":"الأربعاء","s_d":62,"s_m":"مارس","l_d":5.859999999987792,"l_m":"صفر","year":869,"status":"كبس"},{"d":317100,"n":"الخميس","s_d":63,"s_m":"مارس","l_d":6.859999999987792,"l_m":"ربيع الأول","year":869,"status":"كبس"},{"d":317101,"n":"الجمعة","s_d":64,"s_m":"مارس","l_d":7.859999999987792,"l_m":"ربيع الأول","year":869,"status":"كبس"},{"d":317102,"n":"السبت","s_d":65,"s_m":"مارس","l_d":8.859999999987792,"l_m":"ربيع الثاني","year":869,"status":"كبس"},{"d":317103,"n":"الأحد","s_d":66,"s_m":"مارس","l_d":9.859999999987792,"l_m":"ربيع الثاني","year":869,"status":"كبس"},{"d":317104,"n":"الاثنين","s_d":67,"s_m":"مارس","l_d":10.859999999987792,"l_m":"جمادى الأول","year":869,"status":"كبس"},{"d":317105,"n":"الثلاثاء","s_d":68,"s_m":"مارس","l_d":11.859999999987792,"l_m":"جمادى الأول","year":869,"status":"كبس"},{"d":317106,"n":"الأربعاء","s_d":69,"s_m":"مارس","l_d":12.859999999987792,"l_m":"جمادى الأول","year":869,"status":"كبس"},{"d":317107,"n":"الخميس","s_d":70,"s_m":"مارس","l_d":13.859999999987792,"l_m":"جمادى الثاني","year":869,"status":"كبس"},{"d":317108,"n":"الجمعة","s_d":71,"s_m":"مارس","l_d":14.859999999987792,"l_m":"جمادى الثاني","year":869,"status":"كبس"},{"d":317109,"n":"السبت","s_d":72,"s_m":"مارس","l_d":15.859999999987792,"l_m":"رجب","year":869,"status":"كبس"},{"d":317110,"n":"الأحد","s_d":73,"s_m":"مارس","l_d":16.859999999987792,"l_m":"رجب","year":869,"status":"كبس"},{"d":317111,"n":"الاثنين","s_d":74,"s_m":"مارس","l_d":17.859999999987792,"l_m":"رجب","year":869,"status":"كبس"},{"d":317112,"n":"الثلاثاء","s_d":75,"s_m":"مارس","l_d":18.859999999987792,"l_m":"شعبان","year":869,"status":"كبس"},{"d":317113,"n":"الأربعاء","s_d":76,"s_m":"مارس","l_d":19.859999999987792,"l_m":"شعبان","year":869,"status":"كبس"},{"d":317114,"n":"الخميس","s_d":77,"s_m":"مارس","l_d":20.859999999987792,"l_m":"رمضان","year":869,"status":"كبس"},{"d":317115,"n":"الجمعة","s_d":78,"s_m":"مارس","l_d":21.859999999987792,"l_m":"رمضان","year":869,"status":"كبس"},{"d":317116,"n":"السبت","s_d":79,"s_m":"مارس","l_d":22.859999999987792,"l_m":"رمضان","year":869,"status":"كبس"},{"d":317117,"n":"الأحد","s_d":80,"s_m":"مارس","l_d":23.859999999987792,"l_m":"شوال","year":869,"status":"كبس"},{"d":317118,"n":"الاثنين","s_d":81,"s_m":"مارس","l_d":24.859999999987792,"l_m":"شوال","year":869,"status":"كبس"},{"d":317119,"n":"الثلاثاء","s_d":82,"s_m":"مارس","l_d":25.859999999987792,"l_m":"ذو القعدة","year":869,"status":"كبس"},{"d":317120,"n":"الأربعاء","s_d":83,"s_m":"مارس","l_d":26.859999999987792,"l_m":"ذو القعدة","year":869,"status":"كبس"},{"d":317121,"n":"الخميس","s_d":84,"s_m":"مارس","l_d":27.859999999987792,"l_m":"ذو القعدة","year":869,"status":"كبس"},{"d":317122,"n":"الجمعة","s_d":85,"s_m":"مارس","l_d":28.859999999987792,"l_m":"ذو الحجة","year":869,"status":"كبس"},{"d":317123,"n":"السبت","s_d":86,"s_m":"مارس","l_d":29.859999999987792,"l_m":"ذو الحجة","year":869,"status":"كبس"},{"d":317124,"n":"الأحد","s_d":87,"s_m":"مارس","l_d":1.3299999999877912,"l_m":"محرم","year":869,"status":"كبس"},{"d":317125,"n":"الاثنين","s_d":88,"s_m":"مارس","l_d":2.329999999987791,"l_m":"محرم","year":869,"status":"كبس"},{"d":317126,"n":"الثلاثاء","s_d":89,"s_m":"مارس","l_d":3.329999999987791,"l_m":"محرم","year":869,"status":"كبس"},{"d":317127,"n":"الأربعاء","s_d":90,"s_m":"مارس","l_d":4.329999999987791,"l_m":"صفر","year":869,"status":"كبس"},{"d":317128,"n":"الخميس","s_d":91,"s_m":"مارس","l_d":5.329999999987791,"l_m":"صفر","year":869,"status":"كبس"},{"d":317129,"n":"الجمعة","s_d":92,"s_m":"أبريل","l_d":6.329999999987791,"l_m":"ربيع الأول","year":869,"status":"كبس"},{"d":317130,"n":"السبت","s_d":93,"s_m":"أبريل","l_d":7.329999999987791,"l_m":"ربيع الأول","year":869,"status":"كبس"},{"d":317131,"n":"الأحد","s_d":94,"s_m":"أبريل","l_d":8.329999999987791,"l_m":"ربيع الأول","year":869,"status":"كبس"},{"d":317132,"n":"الاثنين","s_d":95,"s_m":"أبريل","l_d":9.329999999987791,"l_m":"ربيع الثاني","year":869,"status":"كبس"},{"d":317133,"n":"الثلاثاء","s_d":96,"s_m":"أبريل","l_d":10.329999999987791,"l_m":"ربيع الثاني","year":869,"status":"كبس"},{"d":317134,"n":"الأربعاء","s_d":97,"s_m":"أبريل","l_d":11.329999999987791,"l_m":"جمادى الأول","year":869,"status":"كبس"},{"d":317135,"n":"الخميس","s_d":98,"s_m":"أبريل","l_d":12.329999999987791,"l_m":"جمادى الأول","year":869,"status":"كبس"},{"d":317136,"n":"الجمعة","s_d":99,"s_m":"أبريل","l_d":13.329999999987791,"l_m":"جمادى الثاني","year":869,"status":"كبس"},{"d":317137,"n":"السبت","s_d":100,"s_m":"أبريل","l_d":14.329999999987791,"l_m":"جمادى الثاني","year":869,"status":"كبس"},{"d":317138,"n":"الأحد","s_d":101,"s_m":"أبريل","l_d":15.329999999987791,"l_m":"جمادى الثاني","year":869,"status":"كبس"},{"d":317139,"n":"الاثنين","s_d":102,"s_m":"أبريل","l_d":16.32999999998779,"l_m":"رجب","year":869,"status":"كبس"},{"d":317140,"n":"الثلاثاء","s_d":103,"s_m":"أبريل","l_d":17.32999999998779,"l_m":"رجب","year":869,"status":"كبس"},{"d":317141,"n":"الأربعاء","s_d":104,"s_m":"أبريل","l_d":18.32999999998779,"l_m":"شعبان","year":869,"status":"كبس"},{"d":317142,"n":"الخميس","s_d":105,"s_m":"أبريل","l_d":19.32999999998779,"l_m":"شعبان","year":869,"status":"كبس"},{"d":317143,"n":"الجمعة","s_d":106,"s_m":"أبريل","l_d":20.32999999998779,"l_m":"شعبان","year":869,"status":"كبس"},{"d":317144,"n":"السبت","s_d":107,"s_m":"أبريل","l_d":21.32999999998779,"l_m":"رمضان","year":869,"status":"كبس"},{"d":317145,"n":"الأحد","s_d":108,"s_m":"أبريل","l_d":22.32999999998779,"l_m":"رمضان","year":869,"status":"كبس"},{"d":317146,"n":"الاثنين","s_d":109,"s_m":"أبريل","l_d":23.32999999998779,"l_m":"شوال","year":869,"status":"كبس"},{"d":317147,"n":"الثلاثاء","s_d":110,"s_m":"أبريل","l_d":24.32999999998779,"l_m":"شوال","year":869,"status":"كبس"},{"d":317148,"n":"الأربعاء","s_d":111,"s_m":"أبريل","l_d":25.32999999998779,"l_m":"شوال","year":869,"status":"كبس"},{"d":317149,"n":"الخميس","s_d":112,"s_m":"أبريل","l_d":26.32999999998779,"l_m":"ذو القعدة","year":869,"status":"كبس"},{"d":317150,"n":"الجمعة","s_d":113,"s_m":"أبريل","l_d":27.32999999998779,"l_m":"ذو القعدة","year":869,"status":"كبس"},{"d":317151,"n":"السبت","s_d":114,"s_m":"أبريل","l_d":28.32999999998779,"l_m":"ذو الحجة","year":869,"status":"كبس"},{"d":317152,"n":"الأحد","s_d":115,"s_m":"أبريل","l_d":29.32999999998779,"l_m":"ذو الحجة","year":869,"status":"كبس"},{"d":317153,"n":"الاثنين","s_d":116,"s_m":"أبريل","l_d":30.32999999998779,"l_m":"ذو الحجة","year":869,"status":"كبس"},{"d":317154,"n":"الثلاثاء","s_d":117,"s_m":"أبريل","l_d":1.79999999998779,"l_m":"محرم","year":869,"status":"كبس"},{"d":317155,"n":"الأربعاء","s_d":118,"s_m":"أبريل","l_d":2.79999999998779,"l_m":"محرم","year":869,"status":"كبس"},{"d":317156,"n":"الخميس","s_d":119,"s_m":"أبريل","l_d":3.79999999998779,"l_m":"صفر","year":869,"status":"كبس"},{"d":317157,"n":"الجمعة","s_d":120,"s_m":"أبريل","l_d":4.79999999998779,"l_m":"صفر","year":869,"status":"كبس"},{"d":317158,"n":"السبت","s_d":121,"s_m":"أبريل","l_d":5.79999999998779,"l_m":"صفر","year":869,"status":"كبس"},{"d":317159,"n":"الأحد","s_d":122,"s_m":"مايو","l_d":6.79999999998779,"l_m":"ربيع الأول","year":869,"status":"كبس"},{"d":317160,"n":"الاثنين","s_d":123,"s_m":"مايو","l_d":7.79999999998779,"l_m":"ربيع الأول","year":869,"status":"كبس"},{"d":317161,"n":"الثلاثاء","s_d":124,"s_m":"مايو","l_d":8.79999999998779,"l_m":"ربيع الثاني","year":869,"status":"كبس"},{"d":317162,"n":"الأربعاء","s_d":125,"s_m":"مايو","l_d":9.79999999998779,"l_m":"ربيع الثاني","year":869,"status":"كبس"},{"d":317163,"n":"الخميس","s_d":126,"s_m":"مايو","l_d":10.79999999998779,"l_m":"ربيع الثاني","year":869,"status":"كبس"},{"d":317164,"n":"الجمعة","s_d":127,"s_m":"مايو","l_d":11.79999999998779,"l_m":"جمادى الأول","year":869,"status":"كبس"},{"d":317165,"n":"السبت","s_d":128,"s_m":"مايو","l_d":12.79999999998779,"l_m":"جمادى الأول","year":869,"status":"كبس"},{"d":317166,"n":"الأحد","s_d":129,"s_m":"مايو","l_d":13.79999999998779,"l_m":"جمادى الثاني","year":869,"status":"كبس"},{"d":317167,"n":"الاثنين","s_d":130,"s_m":"مايو","l_d":14.79999999998779,"l_m":"جمادى الثاني","year":869,"status":"كبس"},{"d":317168,"n":"الثلاثاء","s_d":131,"s_m":"مايو","l_d":15.79999999998779,"l_m":"رجب","year":869,"status":"كبس"},{"d":317169,"n":"الأربعاء","s_d":132,"s_m":"مايو","l_d":16.79999999998779,"l_m":"رجب","year":869,"status":"كبس"},{"d":317170,"n":"الخميس","s_d":133,"s_m":"مايو","l_d":17.79999999998779,"l_m":"رجب","year":869,"status":"كبس"},{"d":317171,"n":"الجمعة","s_d":134,"s_m":"مايو","l_d":18.79999999998779,"l_m":"شعبان","year":869,"status":"كبس"},{"d":317172,"n":"السبت","s_d":135,"s_m":"مايو","l_d":19.79999999998779,"l_m":"شعبان","year":869,"status":"كبس"},{"d":317173,"n":"الأحد","s_d":136,"s_m":"مايو","l_d":20.79999999998779,"l_m":"رمضان","year":869,"status":"كبس"},{"d":317174,"n":"الاثنين","s_d":137,"s_m":"مايو","l_d":21.79999999998779,"l_m":"رمضان","year":869,"status":"كبس"},{"d":317175,"n":"الثلاثاء","s_d":138,"s_m":"مايو","l_d":22.79999999998779,"l_m":"رمضان","year":869,"status":"كبس"},{"d":317176,"n":"الأربعاء","s_d":139,"s_m":"مايو","l_d":23.79999999998779,"l_m":"شوال","year":869,"status":"كبس"},{"d":317177,"n":"الخميس","s_d":140,"s_m":"مايو","l_d":24.79999999998779,"l_m":"شوال","year":869,"status":"كبس"},{"d":317178,"n":"الجمعة","s_d":141,"s_m":"مايو","l_d":25.79999999998779,"l_m":"ذو القعدة","year":869,"status":"كبس"},{"d":317179,"n":"السبت","s_d":142,"s_m":"مايو","l_d":26.79999999998779,"l_m":"ذو القعدة","year":869,"status":"كبس"},{"d":317180,"n":"الأحد","s_d":143,"s_m":"مايو","l_d":27.79999999998779,"l_m":"ذو القعدة","year":869,"status":"كبس"},{"d":317181,"n":"الاثنين","s_d":144,"s_m":"مايو","l_d":28.79999999998779,"l_m":"ذو الحجة","year":869,"status":"كبس"},{"d":317182,"n":"الثلاثاء","s_d":145,"s_m":"مايو","l_d":29.79999999998779,"l_m":"ذو الحجة","year":869,"status":"كبس"},{"d":317183,"n":"الأربعاء","s_d":146,"s_m":"مايو","l_d":1.269999999987789,"l_m":"محرم","year":869,"status":"كبس"},{"d":317184,"n":"الخميس","s_d":147,"s_m":"مايو","l_d":2.269999999987789,"l_m":"محرم","year":869,"status":"كبس"},{"d":317185,"n":"الجمعة","s_d":148,"s_m":"مايو","l_d":3.269999999987789,"l_m":"محرم","year":869,"status":"كبس"},{"d":317186,"n":"السبت","s_d":149,"s_m":"مايو","l_d":4.269999999987789,"l_m":"صفر","year":869,"status":"كبس"},{"d":317187,"n":"الأحد","s_d":150,"s_m":"مايو","l_d":5.269999999987789,"l_m":"صفر","year":869,"status":"كبس"},{"d":317188,"n":"الاثنين","s_d":151,"s_m":"مايو","l_d":6.269999999987789,"l_m":"ربيع الأول","year":869,"status":"كبس"},{"d":317189,"n":"الثلاثاء","s_d":152,"s_m":"مايو","l_d":7.269999999987789,"l_m":"ربيع الأول","year":869,"status":"كبس"},{"d":317190,"n":"الأربعاء","s_d":153,"s_m":"يونيو","l_d":8.269999999987789,"l_m":"ربيع الأول","year":869,"status":"كبس"},{"d":317191,"n":"الخميس","s_d":154,"s_m":"يونيو","l_d":9.269999999987789,"l_m":"ربيع الثاني","year":869,"status":"كبس"},{"d":317192,"n":"الجمعة","s_d":155,"s_m":"يونيو","l_d":10.269999999987789,"l_m":"ربيع الثاني","year":869,"status":"كبس"},{"d":317193,"n":"السبت","s_d":156,"s_m":"يونيو","l_d":11.269999999987789,"l_m":"جمادى الأول","year":869,"status":"كبس"},{"d":317194,"n":"الأحد","s_d":157,"s_m":"يونيو","l_d":12.269999999987789,"l_m":"جمادى الأول","year":869,"status":"كبس"},{"d":317195,"n":"الاثنين","s_d":158,"s_m":"يونيو","l_d":13.269999999987789,"l_m":"جمادى الأول","year":869,"status":"كبس"},{"d":317196,"n":"الثلاثاء","s_d":159,"s_m":"يونيو","l_d":14.269999999987789,"l_m":"جمادى الثاني","year":869,"status":"كبس"},{"d":317197,"n":"الأربعاء","s_d":160,"s_m":"يونيو","l_d":15.269999999987789,"l_m":"جمادى الثاني","year":869,"status":"كبس"},{"d":317198,"n":"الخميس","s_d":161,"s_m":"يونيو","l_d":16.26999999998779,"l_m":"رجب","year":869,"status":"كبس"},{"d":317199,"n":"الجمعة","s_d":162,"s_m":"يونيو","l_d":17.26999999998779,"l_m":"رجب","year":869,"status":"كبس"},{"d":317200,"n":"السبت","s_d":163,"s_m":"يونيو","l_d":18.26999999998779,"l_m":"شعبان","year":869,"status":"كبس"},{"d":317201,"n":"الأحد","s_d":164,"s_m":"يونيو","l_d":19.26999999998779,"l_m":"شعبان","year":869,"status":"كبس"},{"d":317202,"n":"الاثنين","s_d":165,"s_m":"يونيو","l_d":20.26999999998779,"l_m":"شعبان","year":869,"status":"كبس"},{"d":317203,"n":"الثلاثاء","s_d":166,"s_m":"يونيو","l_d":21.26999999998779,"l_m":"رمضان","year":869,"status":"كبس"},{"d":317204,"n":"الأربعاء","s_d":167,"s_m":"يونيو","l_d":22.26999999998779,"l_m":"رمضان","year":869,"status":"كبس"},{"d":317205,"n":"الخميس","s_d":168,"s_m":"يونيو","l_d":23.26999999998779,"l_m":"شوال","year":869,"status":"كبس"},{"d":317206,"n":"الجمعة","s_d":169,"s_m":"يونيو","l_d":24.26999999998779,"l_m":"شوال","year":869,"status":"كبس"},{"d":317207,"n":"السبت","s_d":170,"s_m":"يونيو","l_d":25.26999999998779,"l_m":"شوال","year":869,"status":"كبس"},{"d":317208,"n":"الأحد","s_d":171,"s_m":"يونيو","l_d":26.26999999998779,"l_m":"ذو القعدة","year":869,"status":"كبس"},{"d":317209,"n":"الاثنين","s_d":172,"s_m":"يونيو","l_d":27.26999999998779,"l_m":"ذو القعدة","year":869,"status":"كبس"},{"d":317210,"n":"الثلاثاء","s_d":173,"s_m":"يونيو","l_d":28.26999999998779,"l_m":"ذو الحجة","year":869,"status":"كبس"},{"d":317211,"n":"الأربعاء","s_d":174,"s_m":"يونيو","l_d":29.26999999998779,"l_m":"ذو الحجة","year":869,"status":"كبس"},{"d":317212,"n":"الخميس","s_d":175,"s_m":"يونيو","l_d":30.26999999998779,"l_m":"ذو الحجة","year":869,"status":"كبس"},{"d":317213,"n":"الجمعة","s_d":176,"s_m":"يونيو","l_d":1.7399999999877878,"l_m":"محرم","year":869,"status":"كبس"},{"d":317214,"n":"السبت","s_d":177,"s_m":"يونيو","l_d":2.7399999999877878,"l_m":"محرم","year":869,"status":"كبس"},{"d":317215,"n":"الأحد","s_d":178,"s_m":"يونيو","l_d":3.7399999999877878,"l_m":"صفر","year":869,"status":"كبس"},{"d":317216,"n":"الاثنين","s_d":179,"s_m":"يونيو","l_d":4.739999999987788,"l_m":"صفر","year":869,"status":"كبس"},{"d":317217,"n":"الثلاثاء","s_d":180,"s_m":"يونيو","l_d":5.739999999987788,"l_m":"صفر","year":869,"status":"كبس"},{"d":317218,"n":"الأربعاء","s_d":181,"s_m":"يونيو","l_d":6.739999999987788,"l_m":"ربيع الأول","year":869,"status":"كبس"},{"d":317219,"n":"الخميس","s_d":182,"s_m":"يونيو","l_d":7.739999999987788,"l_m":"ربيع الأول","year":869,"status":"كبس"},{"d":317220,"n":"الجمعة","s_d":183,"s_m":"يوليو","l_d":8.739999999987788,"l_m":"ربيع الثاني","year":869,"status":"كبس"},{"d":317221,"n":"السبت","s_d":184,"s_m":"يوليو","l_d":9.739999999987788,"l_m":"ربيع الثاني","year":869,"status":"كبس"},{"d":317222,"n":"الأحد","s_d":185,"s_m":"يوليو","l_d":10.739999999987788,"l_m":"ربيع الثاني","year":869,"status":"كبس"},{"d":317223,"n":"الاثنين","s_d":186,"s_m":"يوليو","l_d":11.739999999987788,"l_m":"جمادى الأول","year":869,"status":"كبس"},{"d":317224,"n":"الثلاثاء","s_d":187,"s_m":"يوليو","l_d":12.739999999987788,"l_m":"جمادى الأول","year":869,"status":"كبس"},{"d":317225,"n":"الأربعاء","s_d":188,"s_m":"يوليو","l_d":13.739999999987788,"l_m":"جمادى الثاني","year":869,"status":"كبس"},{"d":317226,"n":"الخميس","s_d":189,"s_m":"يوليو","l_d":14.739999999987788,"l_m":"جمادى الثاني","year":869,"status":"كبس"},{"d":317227,"n":"الجمعة","s_d":190,"s_m":"يوليو","l_d":15.739999999987788,"l_m":"جمادى الثاني","year":869,"status":"كبس"},{"d":317228,"n":"السبت","s_d":191,"s_m":"يوليو","l_d":16.739999999987788,"l_m":"رجب","year":869,"status":"كبس"},{"d":317229,"n":"الأحد","s_d":192,"s_m":"يوليو","l_d":17.739999999987788,"l_m":"رجب","year":869,"status":"كبس"},{"d":317230,"n":"الاثنين","s_d":193,"s_m":"يوليو","l_d":18.739999999987788,"l_m":"شعبان","year":869,"status":"كبس"},{"d":317231,"n":"الثلاثاء","s_d":194,"s_m":"يوليو","l_d":19.739999999987788,"l_m":"شعبان","year":869,"status":"كبس"},{"d":317232,"n":"الأربعاء","s_d":195,"s_m":"يوليو","l_d":20.739999999987788,"l_m":"رمضان","year":869,"status":"كبس"},{"d":317233,"n":"الخميس","s_d":196,"s_m":"يوليو","l_d":21.739999999987788,"l_m":"رمضان","year":869,"status":"كبس"},{"d":317234,"n":"الجمعة","s_d":197,"s_m":"يوليو","l_d":22.739999999987788,"l_m":"رمضان","year":869,"status":"كبس"},{"d":317235,"n":"السبت","s_d":198,"s_m":"يوليو","l_d":23.739999999987788,"l_m":"شوال","year":869,"status":"كبس"},{"d":317236,"n":"الأحد","s_d":199,"s_m":"يوليو","l_d":24.739999999987788,"l_m":"شوال","year":869,"status":"كبس"},{"d":317237,"n":"الاثنين","s_d":200,"s_m":"يوليو","l_d":25.739999999987788,"l_m":"ذو القعدة","year":869,"status":"كبس"},{"d":317238,"n":"الثلاثاء","s_d":201,"s_m":"يوليو","l_d":26.739999999987788,"l_m":"ذو القعدة","year":869,"status":"كبس"},{"d":317239,"n":"الأربعاء","s_d":202,"s_m":"يوليو","l_d":27.739999999987788,"l_m":"ذو القعدة","year":869,"status":"كبس"},{"d":317240,"n":"الخميس","s_d":203,"s_m":"يوليو","l_d":28.739999999987788,"l_m":"ذو الحجة","year":869,"status":"كبس"},{"d":317241,"n":"الجمعة","s_d":204,"s_m":"يوليو","l_d":29.739999999987788,"l_m":"ذو الحجة","year":869,"status":"كبس"},{"d":317242,"n":"السبت","s_d":205,"s_m":"يوليو","l_d":1.2099999999877866,"l_m":"محرم","year":869,"status":"كبس"},{"d":317243,"n":"الأحد","s_d":206,"s_m":"يوليو","l_d":2.2099999999877866,"l_m":"محرم","year":869,"status":"كبس"},{"d":317244,"n":"الاثنين","s_d":207,"s_m":"يوليو","l_d":3.2099999999877866,"l_m":"محرم","year":869,"status":"كبس"},{"d":317245,"n":"الثلاثاء","s_d":208,"s_m":"يوليو","l_d":4.209999999987787,"l_m":"صفر","year":869,"status":"كبس"},{"d":317246,"n":"الأربعاء","s_d":209,"s_m":"يوليو","l_d":5.209999999987787,"l_m":"صفر","year":869,"status":"كبس"},{"d":317247,"n":"الخميس","s_d":210,"s_m":"يوليو","l_d":6.209999999987787,"l_m":"ربيع الأول","year":869,"status":"كبس"},{"d":317248,"n":"الجمعة","s_d":211,"s_m":"يوليو","l_d":7.209999999987787,"l_m":"ربيع الأول","year":869,"status":"كبس"},{"d":317249,"n":"السبت","s_d":212,"s_m":"يوليو","l_d":8.209999999987787,"l_m":"ربيع الأول","year":869,"status":"كبس"},{"d":317250,"n":"الأحد","s_d":213,"s_m":"يوليو","l_d":9.209999999987787,"l_m":"ربيع الثاني","year":869,"status":"كبس"},{"d":317251,"n":"الاثنين","s_d":214,"s_m":"أغسطس","l_d":10.209999999987787,"l_m":"ربيع الثاني","year":869,"status":"كبس"},{"d":317252,"n":"الثلاثاء","s_d":215,"s_m":"أغسطس","l_d":11.209999999987787,"l_m":"جمادى الأول","year":869,"status":"كبس"},{"d":317253,"n":"الأربعاء","s_d":216,"s_m":"أغسطس","l_d":12.209999999987787,"l_m":"جمادى الأول","year":869,"status":"كبس"},{"d":317254,"n":"الخميس","s_d":217,"s_m":"أغسطس","l_d":13.209999999987787,"l_m":"جمادى الأول","year":869,"status":"كبس"},{"d":317255,"n":"الجمعة","s_d":218,"s_m":"أغسطس","l_d":14.209999999987787,"l_m":"جمادى الثاني","year":869,"status":"كبس"},{"d":317256,"n":"السبت","s_d":219,"s_m":"أغسطس","l_d":15.209999999987787,"l_m":"جمادى الثاني","year":869,"status":"كبس"},{"d":317257,"n":"الأحد","s_d":220,"s_m":"أغسطس","l_d":16.209999999987787,"l_m":"رجب","year":869,"status":"كبس"},{"d":317258,"n":"الاثنين","s_d":221,"s_m":"أغسطس","l_d":17.209999999987787,"l_m":"رجب","year":869,"status":"كبس"},{"d":317259,"n":"الثلاثاء","s_d":222,"s_m":"أغسطس","l_d":18.209999999987787,"l_m":"رجب","year":869,"status":"كبس"},{"d":317260,"n":"الأربعاء","s_d":223,"s_m":"أغسطس","l_d":19.209999999987787,"l_m":"شعبان","year":869,"status":"كبس"},{"d":317261,"n":"الخميس","s_d":224,"s_m":"أغسطس","l_d":20.209999999987787,"l_m":"شعبان","year":869,"status":"كبس"},{"d":317262,"n":"الجمعة","s_d":225,"s_m":"أغسطس","l_d":21.209999999987787,"l_m":"رمضان","year":869,"status":"كبس"},{"d":317263,"n":"السبت","s_d":226,"s_m":"أغسطس","l_d":22.209999999987787,"l_m":"رمضان","year":869,"status":"كبس"},{"d":317264,"n":"الأحد","s_d":227,"s_m":"أغسطس","l_d":23.209999999987787,"l_m":"شوال","year":869,"status":"كبس"},{"d":317265,"n":"الاثنين","s_d":228,"s_m":"أغسطس","l_d":24.209999999987787,"l_m":"شوال","year":869,"status":"كبس"},{"d":317266,"n":"الثلاثاء","s_d":229,"s_m":"أغسطس","l_d":25.209999999987787,"l_m":"شوال","year":869,"status":"كبس"},{"d":317267,"n":"الأربعاء","s_d":230,"s_m":"أغسطس","l_d":26.209999999987787,"l_m":"ذو القعدة","year":869,"status":"كبس"},{"d":317268,"n":"الخميس","s_d":231,"s_m":"أغسطس","l_d":27.209999999987787,"l_m":"ذو القعدة","year":869,"status":"كبس"},{"d":317269,"n":"الجمعة","s_d":232,"s_m":"أغسطس","l_d":28.209999999987787,"l_m":"ذو الحجة","year":869,"status":"كبس"},{"d":317270,"n":"السبت","s_d":233,"s_m":"أغسطس","l_d":29.209999999987787,"l_m":"ذو الحجة","year":869,"status":"كبس"},{"d":317271,"n":"الأحد","s_d":234,"s_m":"أغسطس","l_d":30.209999999987787,"l_m":"ذو الحجة","year":869,"status":"كبس"},{"d":317272,"n":"الاثنين","s_d":235,"s_m":"أغسطس","l_d":1.6799999999877855,"l_m":"محرم","year":869,"status":"كبس"},{"d":317273,"n":"الثلاثاء","s_d":236,"s_m":"أغسطس","l_d":2.6799999999877855,"l_m":"محرم","year":869,"status":"كبس"},{"d":317274,"n":"الأربعاء","s_d":237,"s_m":"أغسطس","l_d":3.6799999999877855,"l_m":"صفر","year":869,"status":"كبس"},{"d":317275,"n":"الخميس","s_d":238,"s_m":"أغسطس","l_d":4.6799999999877855,"l_m":"صفر","year":869,"status":"كبس"},{"d":317276,"n":"الجمعة","s_d":239,"s_m":"أغسطس","l_d":5.6799999999877855,"l_m":"صفر","year":869,"status":"كبس"},{"d":317277,"n":"السبت","s_d":240,"s_m":"أغسطس","l_d":6.6799999999877855,"l_m":"ربيع الأول","year":869,"status":"كبس"},{"d":317278,"n":"الأحد","s_d":241,"s_m":"أغسطس","l_d":7.6799999999877855,"l_m":"ربيع الأول","year":869,"status":"كبس"},{"d":317279,"n":"الاثنين","s_d":242,"s_m":"أغسطس","l_d":8.679999999987785,"l_m":"ربيع الثاني","year":869,"status":"كبس"},{"d":317280,"n":"الثلاثاء","s_d":243,"s_m":"أغسطس","l_d":9.679999999987785,"l_m":"ربيع الثاني","year":869,"status":"كبس"},{"d":317281,"n":"الأربعاء","s_d":244,"s_m":"سبتمبر","l_d":10.679999999987785,"l_m":"ربيع الثاني","year":869,"status":"كبس"},{"d":317282,"n":"الخميس","s_d":245,"s_m":"سبتمبر","l_d":11.679999999987785,"l_m":"جمادى الأول","year":869,"status":"كبس"},{"d":317283,"n":"الجمعة","s_d":246,"s_m":"سبتمبر","l_d":12.679999999987785,"l_m":"جمادى الأول","year":869,"status":"كبس"},{"d":317284,"n":"السبت","s_d":247,"s_m":"سبتمبر","l_d":13.679999999987785,"l_m":"جمادى الثاني","year":869,"status":"كبس"},{"d":317285,"n":"الأحد","s_d":248,"s_m":"سبتمبر","l_d":14.679999999987785,"l_m":"جمادى الثاني","year":869,"status":"كبس"},{"d":317286,"n":"الاثنين","s_d":249,"s_m":"سبتمبر","l_d":15.679999999987785,"l_m":"جمادى الثاني","year":869,"status":"كبس"},{"d":317287,"n":"الثلاثاء","s_d":250,"s_m":"سبتمبر","l_d":16.679999999987785,"l_m":"رجب","year":869,"status":"كبس"},{"d":317288,"n":"الأربعاء","s_d":251,"s_m":"سبتمبر","l_d":17.679999999987785,"l_m":"رجب","year":869,"status":"كبس"},{"d":317289,"n":"الخميس","s_d":252,"s_m":"سبتمبر","l_d":18.679999999987785,"l_m":"شعبان","year":869,"status":"كبس"},{"d":317290,"n":"الجمعة","s_d":253,"s_m":"سبتمبر","l_d":19.679999999987785,"l_m":"شعبان","year":869,"status":"كبس"},{"d":317291,"n":"السبت","s_d":254,"s_m":"سبتمبر","l_d":20.679999999987785,"l_m":"شعبان","year":869,"status":"كبس"},{"d":317292,"n":"الأحد","s_d":255,"s_m":"سبتمبر","l_d":21.679999999987785,"l_m":"رمضان","year":869,"status":"كبس"},{"d":317293,"n":"الاثنين","s_d":256,"s_m":"سبتمبر","l_d":22.679999999987785,"l_m":"رمضان","year":869,"status":"كبس"},{"d":317294,"n":"الثلاثاء","s_d":257,"s_m":"سبتمبر","l_d":23.679999999987785,"l_m":"شوال","year":869,"status":"كبس"},{"d":317295,"n":"الأربعاء","s_d":258,"s_m":"سبتمبر","l_d":24.679999999987785,"l_m":"شوال","year":869,"status":"كبس"},{"d":317296,"n":"الخميس","s_d":259,"s_m":"سبتمبر","l_d":25.679999999987785,"l_m":"ذو القعدة","year":869,"status":"كبس"},{"d":317297,"n":"الجمعة","s_d":260,"s_m":"سبتمبر","l_d":26.679999999987785,"l_m":"ذو القعدة","year":869,"status":"كبس"},{"d":317298,"n":"السبت","s_d":261,"s_m":"سبتمبر","l_d":27.679999999987785,"l_m":"ذو القعدة","year":869,"status":"كبس"},{"d":317299,"n":"الأحد","s_d":262,"s_m":"سبتمبر","l_d":28.679999999987785,"l_m":"ذو الحجة","year":869,"status":"كبس"},{"d":317300,"n":"الاثنين","s_d":263,"s_m":"سبتمبر","l_d":29.679999999987785,"l_m":"ذو الحجة","year":869,"status":"كبس"},{"d":317301,"n":"الثلاثاء","s_d":264,"s_m":"سبتمبر","l_d":1.1499999999877843,"l_m":"محرم","year":869,"status":"كبس"},{"d":317302,"n":"الأربعاء","s_d":265,"s_m":"سبتمبر","l_d":2.1499999999877843,"l_m":"محرم","year":869,"status":"كبس"},{"d":317303,"n":"الخميس","s_d":266,"s_m":"سبتمبر","l_d":3.1499999999877843,"l_m":"محرم","year":869,"status":"كبس"},{"d":317304,"n":"الجمعة","s_d":267,"s_m":"سبتمبر","l_d":4.149999999987784,"l_m":"صفر","year":869,"status":"كبس"},{"d":317305,"n":"السبت","s_d":268,"s_m":"سبتمبر","l_d":5.149999999987784,"l_m":"صفر","year":869,"status":"كبس"},{"d":317306,"n":"الأحد","s_d":269,"s_m":"سبتمبر","l_d":6.149999999987784,"l_m":"ربيع الأول","year":869,"status":"كبس"},{"d":317307,"n":"الاثنين","s_d":270,"s_m":"سبتمبر","l_d":7.149999999987784,"l_m":"ربيع الأول","year":869,"status":"كبس"},{"d":317308,"n":"الثلاثاء","s_d":271,"s_m":"سبتمبر","l_d":8.149999999987784,"l_m":"ربيع الأول","year":869,"status":"كبس"},{"d":317309,"n":"الأربعاء","s_d":272,"s_m":"سبتمبر","l_d":9.149999999987784,"l_m":"ربيع الثاني","year":869,"status":"كبس"},{"d":317310,"n":"الخميس","s_d":273,"s_m":"سبتمبر","l_d":10.149999999987784,"l_m":"ربيع الثاني","year":869,"status":"كبس"},{"d":317311,"n":"الجمعة","s_d":274,"s_m":"سبتمبر","l_d":11.149999999987784,"l_m":"جمادى الأول","year":869,"status":"كبس"},{"d":317312,"n":"السبت","s_d":275,"s_m":"أكتوبر","l_d":12.149999999987784,"l_m":"جمادى الأول","year":869,"status":"كبس"},{"d":317313,"n":"الأحد","s_d":276,"s_m":"أكتوبر","l_d":13.149999999987784,"l_m":"جمادى الأول","year":869,"status":"كبس"},{"d":317314,"n":"الاثنين","s_d":277,"s_m":"أكتوبر","l_d":14.149999999987784,"l_m":"جمادى الثاني","year":869,"status":"كبس"},{"d":317315,"n":"الثلاثاء","s_d":278,"s_m":"أكتوبر","l_d":15.149999999987784,"l_m":"جمادى الثاني","year":869,"status":"كبس"},{"d":317316,"n":"الأربعاء","s_d":279,"s_m":"أكتوبر","l_d":16.149999999987784,"l_m":"رجب","year":869,"status":"كبس"},{"d":317317,"n":"الخميس","s_d":280,"s_m":"أكتوبر","l_d":17.149999999987784,"l_m":"رجب","year":869,"status":"كبس"},{"d":317318,"n":"الجمعة","s_d":281,"s_m":"أكتوبر","l_d":18.149999999987784,"l_m":"رجب","year":869,"status":"كبس"},{"d":317319,"n":"السبت","s_d":282,"s_m":"أكتوبر","l_d":19.149999999987784,"l_m":"شعبان","year":869,"status":"كبس"},{"d":317320,"n":"الأحد","s_d":283,"s_m":"أكتوبر","l_d":20.149999999987784,"l_m":"شعبان","year":869,"status":"كبس"},{"d":317321,"n":"الاثنين","s_d":284,"s_m":"أكتوبر","l_d":21.149999999987784,"l_m":"رمضان","year":869,"status":"كبس"},{"d":317322,"n":"الثلاثاء","s_d":285,"s_m":"أكتوبر","l_d":22.149999999987784,"l_m":"رمضان","year":869,"status":"كبس"},{"d":317323,"n":"الأربعاء","s_d":286,"s_m":"أكتوبر","l_d":23.149999999987784,"l_m":"شوال","year":869,"status":"كبس"},{"d":317324,"n":"الخميس","s_d":287,"s_m":"أكتوبر","l_d":24.149999999987784,"l_m":"شوال","year":869,"status":"كبس"},{"d":317325,"n":"الجمعة","s_d":288,"s_m":"أكتوبر","l_d":25.149999999987784,"l_m":"شوال","year":869,"status":"كبس"},{"d":317326,"n":"السبت","s_d":289,"s_m":"أكتوبر","l_d":26.149999999987784,"l_m":"ذو القعدة","year":869,"status":"كبس"},{"d":317327,"n":"الأحد","s_d":290,"s_m":"أكتوبر","l_d":27.149999999987784,"l_m":"ذو القعدة","year":869,"status":"كبس"},{"d":317328,"n":"الاثنين","s_d":291,"s_m":"أكتوبر","l_d":28.149999999987784,"l_m":"ذو الحجة","year":869,"status":"كبس"},{"d":317329,"n":"الثلاثاء","s_d":292,"s_m":"أكتوبر","l_d":29.149999999987784,"l_m":"ذو الحجة","year":869,"status":"كبس"},{"d":317330,"n":"الأربعاء","s_d":293,"s_m":"أكتوبر","l_d":30.149999999987784,"l_m":"ذو الحجة","year":869,"status":"كبس"},{"d":317331,"n":"الخميس","s_d":294,"s_m":"أكتوبر","l_d":1.6199999999877832,"l_m":"محرم","year":869,"status":"كبس"},{"d":317332,"n":"الجمعة","s_d":295,"s_m":"أكتوبر","l_d":2.619999999987783,"l_m":"محرم","year":869,"status":"كبس"},{"d":317333,"n":"السبت","s_d":296,"s_m":"أكتوبر","l_d":3.619999999987783,"l_m":"صفر","year":869,"status":"كبس"},{"d":317334,"n":"الأحد","s_d":297,"s_m":"أكتوبر","l_d":4.619999999987783,"l_m":"صفر","year":869,"status":"كبس"},{"d":317335,"n":"الاثنين","s_d":298,"s_m":"أكتوبر","l_d":5.619999999987783,"l_m":"صفر","year":869,"status":"كبس"},{"d":317336,"n":"الثلاثاء","s_d":299,"s_m":"أكتوبر","l_d":6.619999999987783,"l_m":"ربيع الأول","year":869,"status":"كبس"},{"d":317337,"n":"الأربعاء","s_d":300,"s_m":"أكتوبر","l_d":7.619999999987783,"l_m":"ربيع الأول","year":869,"status":"كبس"},{"d":317338,"n":"الخميس","s_d":301,"s_m":"أكتوبر","l_d":8.619999999987783,"l_m":"ربيع الثاني","year":869,"status":"كبس"},{"d":317339,"n":"الجمعة","s_d":302,"s_m":"أكتوبر","l_d":9.619999999987783,"l_m":"ربيع الثاني","year":869,"status":"كبس"},{"d":317340,"n":"السبت","s_d":303,"s_m":"أكتوبر","l_d":10.619999999987783,"l_m":"ربيع الثاني","year":869,"status":"كبس"},{"d":317341,"n":"الأحد","s_d":304,"s_m":"أكتوبر","l_d":11.619999999987783,"l_m":"جمادى الأول","year":869,"status":"كبس"},{"d":317342,"n":"الاثنين","s_d":305,"s_m":"نوفمبر","l_d":12.619999999987783,"l_m":"جمادى الأول","year":869,"status":"كبس"},{"d":317343,"n":"الثلاثاء","s_d":306,"s_m":"نوفمبر","l_d":13.619999999987783,"l_m":"جمادى الثاني","year":869,"status":"كبس"},{"d":317344,"n":"الأربعاء","s_d":307,"s_m":"نوفمبر","l_d":14.619999999987783,"l_m":"جمادى الثاني","year":869,"status":"كبس"},{"d":317345,"n":"الخميس","s_d":308,"s_m":"نوفمبر","l_d":15.619999999987783,"l_m":"جمادى الثاني","year":869,"status":"كبس"},{"d":317346,"n":"الجمعة","s_d":309,"s_m":"نوفمبر","l_d":16.619999999987783,"l_m":"رجب","year":869,"status":"كبس"},{"d":317347,"n":"السبت","s_d":310,"s_m":"نوفمبر","l_d":17.619999999987783,"l_m":"رجب","year":869,"status":"كبس"},{"d":317348,"n":"الأحد","s_d":311,"s_m":"نوفمبر","l_d":18.619999999987783,"l_m":"شعبان","year":869,"status":"كبس"},{"d":317349,"n":"الاثنين","s_d":312,"s_m":"نوفمبر","l_d":19.619999999987783,"l_m":"شعبان","year":869,"status":"كبس"},{"d":317350,"n":"الثلاثاء","s_d":313,"s_m":"نوفمبر","l_d":20.619999999987783,"l_m":"شعبان","year":869,"status":"كبس"},{"d":317351,"n":"الأربعاء","s_d":314,"s_m":"نوفمبر","l_d":21.619999999987783,"l_m":"رمضان","year":869,"status":"كبس"},{"d":317352,"n":"الخميس","s_d":315,"s_m":"نوفمبر","l_d":22.619999999987783,"l_m":"رمضان","year":869,"status":"كبس"},{"d":317353,"n":"الجمعة","s_d":316,"s_m":"نوفمبر","l_d":23.619999999987783,"l_m":"شوال","year":869,"status":"كبس"},{"d":317354,"n":"السبت","s_d":317,"s_m":"نوفمبر","l_d":24.619999999987783,"l_m":"شوال","year":869,"status":"كبس"},{"d":317355,"n":"الأحد","s_d":318,"s_m":"نوفمبر","l_d":25.619999999987783,"l_m":"ذو القعدة","year":869,"status":"كبس"},{"d":317356,"n":"الاثنين","s_d":319,"s_m":"نوفمبر","l_d":26.619999999987783,"l_m":"ذو القعدة","year":869,"status":"كبس"},{"d":317357,"n":"الثلاثاء","s_d":320,"s_m":"نوفمبر","l_d":27.619999999987783,"l_m":"ذو القعدة","year":869,"status":"كبس"},{"d":317358,"n":"الأربعاء","s_d":321,"s_m":"نوفمبر","l_d":28.619999999987783,"l_m":"ذو الحجة","year":869,"status":"كبس"},{"d":317359,"n":"الخميس","s_d":322,"s_m":"نوفمبر","l_d":29.619999999987783,"l_m":"ذو الحجة","year":869,"status":"كبس"},{"d":317360,"n":"الجمعة","s_d":323,"s_m":"نوفمبر","l_d":1.089999999987782,"l_m":"محرم","year":869,"status":"كبس"},{"d":317361,"n":"السبت","s_d":324,"s_m":"نوفمبر","l_d":2.089999999987782,"l_m":"محرم","year":869,"status":"كبس"},{"d":317362,"n":"الأحد","s_d":325,"s_m":"نوفمبر","l_d":3.089999999987782,"l_m":"محرم","year":869,"status":"كبس"},{"d":317363,"n":"الاثنين","s_d":326,"s_m":"نوفمبر","l_d":4.089999999987782,"l_m":"صفر","year":869,"status":"كبس"},{"d":317364,"n":"الثلاثاء","s_d":327,"s_m":"نوفمبر","l_d":5.089999999987782,"l_m":"صفر","year":869,"status":"كبس"},{"d":317365,"n":"الأربعاء","s_d":328,"s_m":"نوفمبر","l_d":6.089999999987782,"l_m":"ربيع الأول","year":869,"status":"كبس"},{"d":317366,"n":"الخميس","s_d":329,"s_m":"نوفمبر","l_d":7.089999999987782,"l_m":"ربيع الأول","year":869,"status":"كبس"},{"d":317367,"n":"الجمعة","s_d":330,"s_m":"نوفمبر","l_d":8.089999999987782,"l_m":"ربيع الأول","year":869,"status":"كبس"},{"d":317368,"n":"السبت","s_d":331,"s_m":"نوفمبر","l_d":9.089999999987782,"l_m":"ربيع الثاني","year":869,"status":"كبس"},{"d":317369,"n":"الأحد","s_d":332,"s_m":"نوفمبر","l_d":10.089999999987782,"l_m":"ربيع الثاني","year":869,"status":"كبس"},{"d":317370,"n":"الاثنين","s_d":333,"s_m":"نوفمبر","l_d":11.089999999987782,"l_m":"جمادى الأول","year":869,"status":"كبس"},{"d":317371,"n":"الثلاثاء","s_d":334,"s_m":"نوفمبر","l_d":12.089999999987782,"l_m":"جمادى الأول","year":869,"status":"كبس"},{"d":317372,"n":"الأربعاء","s_d":335,"s_m":"نوفمبر","l_d":13.089999999987782,"l_m":"جمادى الأول","year":869,"status":"كبس"},{"d":317373,"n":"الخميس","s_d":336,"s_m":"ديسمبر","l_d":14.089999999987782,"l_m":"جمادى الثاني","year":869,"status":"كبس"},{"d":317374,"n":"الجمعة","s_d":337,"s_m":"ديسمبر","l_d":15.089999999987782,"l_m":"جمادى الثاني","year":869,"status":"كبس"},{"d":317375,"n":"السبت","s_d":338,"s_m":"ديسمبر","l_d":16.089999999987782,"l_m":"رجب","year":869,"status":"كبس"},{"d":317376,"n":"الأحد","s_d":339,"s_m":"ديسمبر","l_d":17.089999999987782,"l_m":"رجب","year":869,"status":"كبس"},{"d":317377,"n":"الاثنين","s_d":340,"s_m":"ديسمبر","l_d":18.089999999987782,"l_m":"رجب","year":869,"status":"كبس"},{"d":317378,"n":"الثلاثاء","s_d":341,"s_m":"ديسمبر","l_d":19.089999999987782,"l_m":"شعبان","year":869,"status":"كبس"},{"d":317379,"n":"الأربعاء","s_d":342,"s_m":"ديسمبر","l_d":20.089999999987782,"l_m":"شعبان","year":869,"status":"كبس"},{"d":317380,"n":"الخميس","s_d":343,"s_m":"ديسمبر","l_d":21.089999999987782,"l_m":"رمضان","year":869,"status":"كبس"},{"d":317381,"n":"الجمعة","s_d":344,"s_m":"ديسمبر","l_d":22.089999999987782,"l_m":"رمضان","year":869,"status":"كبس"},{"d":317382,"n":"السبت","s_d":345,"s_m":"ديسمبر","l_d":23.089999999987782,"l_m":"رمضان","year":869,"status":"كبس"},{"d":317383,"n":"الأحد","s_d":346,"s_m":"ديسمبر","l_d":24.089999999987782,"l_m":"شوال","year":869,"status":"كبس"},{"d":317384,"n":"الاثنين","s_d":347,"s_m":"ديسمبر","l_d":25.089999999987782,"l_m":"شوال","year":869,"status":"كبس"},{"d":317385,"n":"الثلاثاء","s_d":348,"s_m":"ديسمبر","l_d":26.089999999987782,"l_m":"ذو القعدة","year":869,"status":"كبس"},{"d":317386,"n":"الأربعاء","s_d":349,"s_m":"ديسمبر","l_d":27.089999999987782,"l_m":"ذو القعدة","year":869,"status":"كبس"},{"d":317387,"n":"الخميس","s_d":350,"s_m":"ديسمبر","l_d":28.089999999987782,"l_m":"ذو الحجة","year":869,"status":"كبس"},{"d":317388,"n":"الجمعة","s_d":351,"s_m":"ديسمبر","l_d":29.089999999987782,"l_m":"ذو الحجة","year":869,"status":"كبس"},{"d":317389,"n":"السبت","s_d":352,"s_m":"ديسمبر","l_d":30.089999999987782,"l_m":"ذو الحجة","year":869,"status":"كبس"},{"d":317390,"n":"الأحد","s_d":353,"s_m":"ديسمبر","l_d":1.559999999987781,"l_m":"محرم","year":869,"status":"كبس"},{"d":317391,"n":"الاثنين","s_d":354,"s_m":"ديسمبر","l_d":2.559999999987781,"l_m":"محرم","year":869,"status":"كبس"},{"d":317392,"n":"الثلاثاء","s_d":355,"s_m":"ديسمبر","l_d":3.559999999987781,"l_m":"صفر","year":869,"status":"كبس"},{"d":317393,"n":"الأربعاء","s_d":356,"s_m":"ديسمبر","l_d":4.559999999987781,"l_m":"صفر","year":869,"status":"كبس"},{"d":317394,"n":"الخميس","s_d":357,"s_m":"ديسمبر","l_d":5.559999999987781,"l_m":"صفر","year":869,"status":"كبس"},{"d":317395,"n":"الجمعة","s_d":358,"s_m":"ديسمبر","l_d":6.559999999987781,"l_m":"ربيع الأول","year":869,"status":"كبس"},{"d":317396,"n":"السبت","s_d":359,"s_m":"ديسمبر","l_d":7.559999999987781,"l_m":"ربيع الأول","year":869,"status":"كبس"},{"d":317397,"n":"الأحد","s_d":360,"s_m":"ديسمبر","l_d":8.559999999987781,"l_m":"ربيع الثاني","year":869,"status":"كبس"},{"d":317398,"n":"الاثنين","s_d":361,"s_m":"ديسمبر","l_d":9.559999999987781,"l_m":"ربيع الثاني","year":869,"status":"كبس"},{"d":317399,"n":"الثلاثاء","s_d":362,"s_m":"ديسمبر","l_d":10.559999999987781,"l_m":"ربيع الثاني","year":869,"status":"كبس"},{"d":317400,"n":"الأربعاء","s_d":363,"s_m":"ديسمبر","l_d":11.559999999987781,"l_m":"جمادى الأول","year":869,"status":"كبس"},{"d":317401,"n":"الخميس","s_d":364,"s_m":"ديسمبر","l_d":12.559999999987781,"l_m":"جمادى الأول","year":869,"status":"كبس"},{"d":317402,"n":"الجمعة","s_d":365,"s_m":"ديسمبر","l_d":13.559999999987781,"l_m":"جمادى الثاني","year":869,"status":"كبس"},{"d":317403,"n":"السبت","s_d":1,"s_m":"يناير","l_d":14.559999999987781,"l_m":"جمادى الثاني","year":870,"status":"كبس"},{"d":317404,"n":"الأحد","s_d":2,"s_m":"يناير","l_d":15.559999999987781,"l_m":"جمادى الثاني","year":870,"status":"كبس"},{"d":317405,"n":"الاثنين","s_d":3,"s_m":"يناير","l_d":16.55999999998778,"l_m":"رجب","year":870,"status":"كبس"},{"d":317406,"n":"الثلاثاء","s_d":4,"s_m":"يناير","l_d":17.55999999998778,"l_m":"رجب","year":870,"status":"كبس"},{"d":317407,"n":"الأربعاء","s_d":5,"s_m":"يناير","l_d":18.55999999998778,"l_m":"شعبان","year":870,"status":"كبس"},{"d":317408,"n":"الخميس","s_d":6,"s_m":"يناير","l_d":19.55999999998778,"l_m":"شعبان","year":870,"status":"كبس"},{"d":317409,"n":"الجمعة","s_d":7,"s_m":"يناير","l_d":20.55999999998778,"l_m":"شعبان","year":870,"status":"كبس"},{"d":317410,"n":"السبت","s_d":8,"s_m":"يناير","l_d":21.55999999998778,"l_m":"رمضان","year":870,"status":"كبس"},{"d":317411,"n":"الأحد","s_d":9,"s_m":"يناير","l_d":22.55999999998778,"l_m":"رمضان","year":870,"status":"كبس"},{"d":317412,"n":"الاثنين","s_d":10,"s_m":"يناير","l_d":23.55999999998778,"l_m":"شوال","year":870,"status":"كبس"},{"d":317413,"n":"الثلاثاء","s_d":11,"s_m":"يناير","l_d":24.55999999998778,"l_m":"شوال","year":870,"status":"كبس"},{"d":317414,"n":"الأربعاء","s_d":12,"s_m":"يناير","l_d":25.55999999998778,"l_m":"شوال","year":870,"status":"كبس"},{"d":317415,"n":"الخميس","s_d":13,"s_m":"يناير","l_d":26.55999999998778,"l_m":"ذو القعدة","year":870,"status":"كبس"},{"d":317416,"n":"الجمعة","s_d":14,"s_m":"يناير","l_d":27.55999999998778,"l_m":"ذو القعدة","year":870,"status":"كبس"},{"d":317417,"n":"السبت","s_d":15,"s_m":"يناير","l_d":28.55999999998778,"l_m":"ذو الحجة","year":870,"status":"كبس"},{"d":317418,"n":"الأحد","s_d":16,"s_m":"يناير","l_d":29.55999999998778,"l_m":"ذو الحجة","year":870,"status":"كبس"},{"d":317419,"n":"الاثنين","s_d":17,"s_m":"يناير","l_d":1.0299999999877798,"l_m":"محرم","year":870,"status":"كبس"},{"d":317420,"n":"الثلاثاء","s_d":18,"s_m":"يناير","l_d":2.02999999998778,"l_m":"محرم","year":870,"status":"كبس"},{"d":317421,"n":"الأربعاء","s_d":19,"s_m":"يناير","l_d":3.02999999998778,"l_m":"محرم","year":870,"status":"كبس"},{"d":317422,"n":"الخميس","s_d":20,"s_m":"يناير","l_d":4.02999999998778,"l_m":"صفر","year":870,"status":"كبس"},{"d":317423,"n":"الجمعة","s_d":21,"s_m":"يناير","l_d":5.02999999998778,"l_m":"صفر","year":870,"status":"كبس"},{"d":317424,"n":"السبت","s_d":22,"s_m":"يناير","l_d":6.02999999998778,"l_m":"ربيع الأول","year":870,"status":"كبس"},{"d":317425,"n":"الأحد","s_d":23,"s_m":"يناير","l_d":7.02999999998778,"l_m":"ربيع الأول","year":870,"status":"كبس"},{"d":317426,"n":"الاثنين","s_d":24,"s_m":"يناير","l_d":8.02999999998778,"l_m":"ربيع الأول","year":870,"status":"كبس"},{"d":317427,"n":"الثلاثاء","s_d":25,"s_m":"يناير","l_d":9.02999999998778,"l_m":"ربيع الثاني","year":870,"status":"كبس"},{"d":317428,"n":"الأربعاء","s_d":26,"s_m":"يناير","l_d":10.02999999998778,"l_m":"ربيع الثاني","year":870,"status":"كبس"},{"d":317429,"n":"الخميس","s_d":27,"s_m":"يناير","l_d":11.02999999998778,"l_m":"جمادى الأول","year":870,"status":"كبس"},{"d":317430,"n":"الجمعة","s_d":28,"s_m":"يناير","l_d":12.02999999998778,"l_m":"جمادى الأول","year":870,"status":"كبس"},{"d":317431,"n":"السبت","s_d":29,"s_m":"يناير","l_d":13.02999999998778,"l_m":"جمادى الأول","year":870,"status":"كبس"},{"d":317432,"n":"الأحد","s_d":30,"s_m":"يناير","l_d":14.02999999998778,"l_m":"جمادى الثاني","year":870,"status":"كبس"}]